http_server_base/__init__.py
http_server_base/__main__.py
http_server_base/ab2.py
http_server_base/application_base.py
http_server_base/daemon.py
http_server_base/discoverable.py
http_server_base/empty_request_handler.py
http_server_base/error_matcher.py
http_server_base/handler_controller.py
http_server_base/health_check_request_handler.py
http_server_base/host.py
http_server_base/logged_request_handler.py
http_server_base/prefix_tree_router.py
http_server_base/request_logger_client.py
http_server_base/responders.py
http_server_base/strict_host_matches.py
http_server_base/subrequest_client.py
http_server_base/auth/__init__.py
http_server_base/auth/api_key_auth_providers.py
http_server_base/auth/auth_providers.py
http_server_base/auth/authorized_client.py
http_server_base/auth/oauth2_model.py
http_server_base/auth/oauth2_provider.py
http_server_base/interfaces/__init__.py
http_server_base/interfaces/iapplication.py
http_server_base/interfaces/idiscoverable.py
http_server_base/interfaces/ihc.py
http_server_base/interfaces/iloggable.py
http_server_base/interfaces/ilrh.py
http_server_base/interfaces/irespondable.py
http_server_base/interfaces/iresponder.py
http_server_base/interfaces/irouter.py
http_server_base/interfaces/types.py
http_server_base/model/__init__.py
http_server_base/model/dataclass_generic_encoder.py
http_server_base/model/dataclass_json_encoder.py
http_server_base/model/encoder_error.py
http_server_base/model/filtering_json_encoder.py
http_server_base/model/iencoder.py
http_server_base/restapi/__init__.py
http_server_base/restapi/base_in_request_router.py
http_server_base/restapi/base_rest_request_handler.py
http_server_base/restapi/path_tree_in_request_router.py
http_server_base/restapi/path_tree_rest_request_handler.py
http_server_base/restapi/prefix_tree_rest_router.py
http_server_base/restapi/regexp_in_request_router.py
http_server_base/restapi/regexp_rest_request_handler.py
http_server_base/restapi/interfaces/__init__.py
http_server_base-2.0.10.dist-info/LICENCE.txt
http_server_base-2.0.10.dist-info/METADATA
http_server_base-2.0.10.dist-info/WHEEL
http_server_base-2.0.10.dist-info/top_level.txt
http_server_base-2.0.10.dist-info/RECORD
