Metadata-Version: 2.1
Name: http-server-base
Version: 2.0.10
Summary: Library for simple HTTP server & REST HTTP server base based on Tornado. Includes: Logging requests and responses with Request Id; Configuration loading; Methods for requests proxying
Home-page: https://gitlab.com/Hares-Lab/libraries/http-server-base
Author: Peter Zaitcev / USSX Hares
Maintainer: Peter Zaitcev / USSX Hares
License: MIT Licence
Keywords: http,tornado,server,http-server,restapi,rest
Platform: UNKNOWN
Classifier: Development Status :: 2 - Pre-Alpha
Classifier: Intended Audience :: Developers
Classifier: License :: OSI Approved :: MIT License
Classifier: Natural Language :: English
Classifier: Operating System :: OS Independent
Classifier: Programming Language :: Python :: 3.6
Classifier: Programming Language :: Python :: 3.7
Classifier: Programming Language :: Python :: 3.8
Classifier: Programming Language :: Python :: 3.9
Classifier: Programming Language :: Python :: 3.10
Classifier: Topic :: Internet :: Proxy Servers
Classifier: Topic :: Internet :: WWW/HTTP :: HTTP Servers
Classifier: Topic :: Internet :: WWW/HTTP
Classifier: Topic :: Internet
Classifier: Topic :: Software Development :: Libraries :: Python Modules
Classifier: Topic :: Software Development :: Libraries
Classifier: Topic :: Utilities
Requires-Python: >=3.6.0
License-File: LICENCE.txt
Requires-Dist: parse (~=1.19.0)
Requires-Dist: dataclasses-json (~=0.5.6)
Requires-Dist: typing-inspect (~=0.7.1)
Requires-Dist: tornado (~=6.1)
Requires-Dist: camel-case-switcher (>=2.0)
Provides-Extra: all
Requires-Dist: lxml ; extra == 'all'
Requires-Dist: unittest-xml-reporting ; extra == 'all'
Provides-Extra: test
Requires-Dist: lxml ; extra == 'test'
Requires-Dist: unittest-xml-reporting ; extra == 'test'
